test_qgra/__init__.py
test_qgra/types.py
test_qgra/constructors/__init__.py
test_qgra/constructors/feature_maps.py
test_qgra/constructors/hea.py
test_qgra/constructors/iia.py
test_qgra/constructors/qft.py
test_qgra/constructors/rydberg_feature_maps.py
test_qgra/constructors/rydberg_hea.py
test_qgra/constructors/utils.py
test_qgra/qinfo_tools/__init__.py
test_qgra/qinfo_tools/qfi.py
test_qgra/qinfo_tools/qng.py
test_qgra/qinfo_tools/spsa.py
test_qgra/qinfo_tools/utils.py
test_qgra-0.2.14.dist-info/METADATA
test_qgra-0.2.14.dist-info/WHEEL
test_qgra-0.2.14.dist-info/RECORD
