Metadata-Version: 2.4
Name: test-qgra
Version: 0.2.14
License: Apache 2.0
Keywords: quantum
Classifier: License :: OSI Approved :: Apache Software License
Classifier: Programming Language :: Python
Classifier: Programming Language :: Python :: 3
Classifier: Programming Language :: Python :: 3.9
Classifier: Programming Language :: Python :: 3.10
Classifier: Programming Language :: Python :: 3.11
Classifier: Programming Language :: Python :: 3.12
Classifier: Programming Language :: Python :: 3.13
Classifier: Programming Language :: Python :: Implementation :: CPython
Classifier: Programming Language :: Python :: Implementation :: PyPy
Requires-Python: <3.14,>=3.9
Requires-Dist: qadence[horqrux,mlflow,pulser]
Requires-Dist: torch
Provides-Extra: visualization
Requires-Dist: graphviz; extra == 'visualization'
